{
  "_fv": 60,
  "_type": "dimension",
  "definition": {
    "biomesInDimension": [
      {
        "value": "CUSTOM:OnShipBiome"
      }
    ],
    "worldGenType": "End like gen",
    "mainFillerBlock": {
      "value": "Blocks.VOID_AIR"
    },
    "fluidBlock": {
      "value": "Blocks.VOID_AIR"
    },
    "canRespawnHere": true,
    "hasFog": false,
    "isDark": false,
    "doesWaterVaporize": false,
    "sleepResult": "ALLOW",
    "hasSkyLight": false,
    "imitateOverworldBehaviour": false,
    "portalFrame": {
      "value": "CUSTOM:Terminidreinforcedwall"
    },
    "portalParticles": {
      "value": "PORTAL"
    },
    "portalLuminance": 2,
    "portalSound": {
      "value": "block.portal.ambient"
    },
    "enableIgniter": false,
    "igniterName": "On Ship Portal Igniter",
    "igniterRarity": "COMMON",
    "specialInformation": {
      "fixedValue": []
    },
    "igniterTab": {
      "value": "TOOLS"
    },
    "texture": "",
    "portalTexture": "automaton_door_bottom",
    "enablePortal": false
  }
}